<?xml version="1.0" encoding="utf-8" ?>
<dwsync>
<file name="AnnotationLink.php" server="184.154.225.17//public_html/" local="129997576800000000" remote="129997576800000000" />
<file name="BooksCategory.php" server="184.154.225.17//public_html/" local="129997576800000000" remote="129997576800000000" />
<file name="BooksLink.php" server="184.154.225.17//public_html/" local="129997576800000000" remote="129997576800000000" />
<file name="Embeddability.php" server="184.154.225.17//public_html/" local="129997576800000000" remote="129997576800000000" />
<file name="InfoLink.php" server="184.154.225.17//public_html/" local="129997576800000000" remote="129997576800000000" />
<file name="PreviewLink.php" server="184.154.225.17//public_html/" local="129997576800000000" remote="129997576800000000" />
<file name="Review.php" server="184.154.225.17//public_html/" local="129997576800000000" remote="129997576800000000" />
<file name="ThumbnailLink.php" server="184.154.225.17//public_html/" local="129997576800000000" remote="129997576800000000" />
<file name="Viewability.php" server="184.154.225.17//public_html/" local="129997576800000000" remote="129997576800000000" />
</dwsync>