<?xml version="1.0" encoding="utf-8" ?>
<dwsync>
<file name="arrow_down.png" server="184.154.225.17//public_html/" local="129997573800000000" remote="129997573800000000" />
<file name="arrow_right.png" server="184.154.225.17//public_html/" local="129997573800000000" remote="129997573800000000" />
<file name="class.png" server="184.154.225.17//public_html/" local="129997573200000000" remote="129997573200000000" />
<file name="constant.png" server="184.154.225.17//public_html/" local="129997573800000000" remote="129997573800000000" />
<file name="favicon.ico" server="184.154.225.17//public_html/" local="129997575600000000" remote="129997575600000000" />
<file name="file-php.png" server="184.154.225.17//public_html/" local="129997573800000000" remote="129997573800000000" />
<file name="function.png" server="184.154.225.17//public_html/" local="129997573800000000" remote="129997573800000000" />
<file name="interface.png" server="184.154.225.17//public_html/" local="129997573800000000" remote="129997573800000000" />
<file name="method.png" server="184.154.225.17//public_html/" local="129997573800000000" remote="129997573800000000" />
<file name="ok.png" server="184.154.225.17//public_html/" local="129997573800000000" remote="129997573800000000" />
<file name="property.png" server="184.154.225.17//public_html/" local="129997573800000000" remote="129997573800000000" />
<file name="variable.png" server="184.154.225.17//public_html/" local="129997575600000000" remote="129997575600000000" />
<file name="visibility_private.png" server="184.154.225.17//public_html/" local="129997573800000000" remote="129997573800000000" />
<file name="visibility_protected.png" server="184.154.225.17//public_html/" local="129997573800000000" remote="129997573800000000" />
<file name="visibility_public.png" server="184.154.225.17//public_html/" local="129997573800000000" remote="129997573800000000" />
</dwsync>